{
    "logisticregression": {
        "val_accuracy": 0.9126984126984127,
        "val_f1": 0.912697627082329,
        "best_params": {
            "C": 5,
            "class_weight": "balanced",
            "max_iter": 500,
            "solver": "lbfgs"
        }
    },
    "randomforest": {
        "val_accuracy": 0.9240362811791383,
        "val_f1": 0.9240180179229932,
        "best_params": {
            "class_weight": "balanced",
            "max_depth": 30,
            "min_samples_split": 10,
            "n_estimators": 300
        }
    }
}